MANIFEST.in
README.md
distribute_setup.py
setup.py
mtgoxexp/__init__.py
mtgoxexp/decorators.py
mtgoxexp/jsonascii.py
python_mtgox_experiment.egg-info/PKG-INFO
python_mtgox_experiment.egg-info/SOURCES.txt
python_mtgox_experiment.egg-info/dependency_links.txt
python_mtgox_experiment.egg-info/top_level.txt